src/__init__.py
src/file_converter.py
src/identity_generator.py
src/main.py
identity_forge-0.0.1.dist-info/LICENSE
identity_forge-0.0.1.dist-info/METADATA
identity_forge-0.0.1.dist-info/WHEEL
identity_forge-0.0.1.dist-info/entry_points.txt
identity_forge-0.0.1.dist-info/top_level.txt
identity_forge-0.0.1.dist-info/RECORD
