Metadata-Version: 2.1
Name: identity-forge
Version: 0.0.1
Home-page: https://anass.ch/projects/
Download-URL: https://github.com/4nass/identity-forge/archive/0.0.1.zip
Author: 4nass
Author-email: contact@anass.ch
Project-URL: Bug Reports, https://github.com/4nass/identity-forge/issues
Requires-Python: >=3.8.0
License-File: LICENSE
Requires-Dist: pandas
Requires-Dist: faker
Requires-Dist: unidecode
Requires-Dist: pytest
Requires-Dist: aiofiles
